porcupy/__init__.py
porcupy/base.py
porcupy/cpo.py
porcupy/cpo_class.py
porcupy/functions.py
porcupy/gpu_cpo.py
porcupy/porcupines.py
porcupy/utils/__init__.py
porcupy/utils/defense_visualization.py
porcupy/utils/enhanced_visualization.py
porcupy/utils/helpers.py
porcupy/utils/interactive_visualization.py
porcupy/utils/plotting.py
porcupy/utils/population.py
porcupy/utils/population_visualization.py
porcupy/utils/visualization.py
porcupy/utils/visualization_manager.py
porcupy-0.2.0.dist-info/licenses/AUTHORS.md
porcupy-0.2.0.dist-info/licenses/LICENSE
porcupy-0.2.0.dist-info/METADATA
porcupy-0.2.0.dist-info/WHEEL
porcupy-0.2.0.dist-info/top_level.txt
porcupy-0.2.0.dist-info/RECORD
