Metadata-Version: 2.4
Name: porcupy
Version: 0.2.0
Summary: Crested Porcupine Optimizer (CPO) with GPU acceleration for optimization problems
Home-page: https://github.com/SammanSarkar/Porcupy
Author: Samman Sarkar
Author-email: Samman Sarkar <sarkar.samman4231@gmail.com>
License: MIT License
Project-URL: Homepage, https://github.com/SammanSarkar/porcupy
Project-URL: Documentation, https://github.com/SammanSarkar/porcupy/tree/main/docs
Project-URL: Issues, https://github.com/SammanSarkar/porcupy/issues
Keywords: optimization,optimization algorithm,crested porcupine optimizer,metaheuristic,nature-inspired,machine learning,artificial intelligence,evolutionary algorithms,global optimization,mathematical optimization,parameter tuning,hyperparameter optimization,gpu-accelerated,parallel computing,scientific computing,benchmark functions,black-box optimization,constrained optimization,mathematical programming,computational intelligence,swarm intelligence,bio-inspired computing
Classifier: Development Status :: 4 - Beta
Classifier: Intended Audience :: Science/Research
Classifier: Intended Audience :: Developers
Classifier: Intended Audience :: Education
Classifier: License :: OSI Approved :: MIT License
Classifier: Programming Language :: Python :: 3
Classifier: Programming Language :: Python :: 3.7
Classifier: Programming Language :: Python :: 3.8
Classifier: Programming Language :: Python :: 3.9
Classifier: Programming Language :: Python :: 3.10
Classifier: Programming Language :: Python :: 3.11
Classifier: Topic :: Scientific/Engineering
Classifier: Topic :: Scientific/Engineering :: Artificial Intelligence
Classifier: Topic :: Scientific/Engineering :: Mathematics
Classifier: Topic :: Scientific/Engineering :: Information Analysis
Classifier: Topic :: Software Development :: Libraries :: Python Modules
Requires-Python: >=3.7
License-File: LICENSE
License-File: AUTHORS.md
Requires-Dist: numpy>=1.19.0
Requires-Dist: scipy>=1.4.0
Provides-Extra: plotting
Requires-Dist: matplotlib>=3.3.0; extra == "plotting"
Provides-Extra: cuda
Requires-Dist: cupy-cuda11x; extra == "cuda"
Provides-Extra: cuda11x
Requires-Dist: cupy-cuda11x; extra == "cuda11x"
Provides-Extra: cuda12x
Requires-Dist: cupy-cuda12x; extra == "cuda12x"
Provides-Extra: gpu-dev
Requires-Dist: cupy-cuda11x; extra == "gpu-dev"
Requires-Dist: pytest>=6.0.0; extra == "gpu-dev"
Requires-Dist: pytest-cov>=2.10.0; extra == "gpu-dev"
Requires-Dist: black>=22.0.0; extra == "gpu-dev"
Requires-Dist: isort>=5.0.0; extra == "gpu-dev"
Requires-Dist: flake8>=3.8.0; extra == "gpu-dev"
Provides-Extra: dev
Requires-Dist: pytest>=6.0.0; extra == "dev"
Requires-Dist: pytest-cov>=2.10.0; extra == "dev"
Requires-Dist: black>=22.0.0; extra == "dev"
Requires-Dist: isort>=5.0.0; extra == "dev"
Requires-Dist: flake8>=3.8.0; extra == "dev"
Provides-Extra: all
Requires-Dist: matplotlib>=3.3.0; extra == "all"
Requires-Dist: pytest>=6.0.0; extra == "all"
Requires-Dist: pytest-cov>=2.10.0; extra == "all"
Requires-Dist: black>=22.0.0; extra == "all"
Requires-Dist: isort>=5.0.0; extra == "all"
Requires-Dist: flake8>=3.8.0; extra == "all"
Dynamic: author
Dynamic: home-page
Dynamic: license-file
Dynamic: requires-python
